CHANGELOG.md
LICENSE.txt
MANIFEST.in
README.md
setup.py
flaskez/__init__.py
flaskez.egg-info/PKG-INFO
flaskez.egg-info/SOURCES.txt
flaskez.egg-info/dependency_links.txt
flaskez.egg-info/requires.txt
flaskez.egg-info/top_level.txt
flaskez/Public/Models.py
flaskez/Public/__init__.py
flaskez/_basic/__init__.py
flaskez/_basic/main_functions.py
flaskez/_models/__init__.py
flaskez/_models/models.py
flaskez/authencation/__init__.py