Metadata-Version: 2.1
Name: flaskez
Version: 0.2.0
Summary: Flaskez is a multipurpose flask extension. It exists both to make creating websites easier, but also to add extra functionality to flask.
Home-page: https://github.com/IHasBone/flaskez
Author: IHasBone
Author-email: info@picstreme.com
License: MIT
Keywords: flask,extension,website,web,site,flask-sqlalchemy,database,sqlalchemy
Classifier: Development Status :: 2 - Pre-Alpha
Classifier: Intended Audience :: Developers
Classifier: Operating System :: OS Independent
Classifier: License :: OSI Approved :: MIT License
Classifier: Programming Language :: Python :: 3
License-File: LICENSE.txt
